{
    "name": "monitors",
    "parent": "null",
    "children": [
      {
        "name": "health",
        "parent": "monitors",
        "children": [
          {
            "name": "effects",
            "parent": "health"
          },
          {
            "name": "electromagnetic",
            "parent": "health"
          }
        ]
      },
      {
        "name": "emissions",
        "parent": "monitors",
        "children": [
          {
            "name": "display",
            "parent": "emissions"
          },
          {
            "name": "magnetic",
            "parent": "emissions"
          }
        ]
      }
    ]
  }